[
  {
    "filename": "1001586-136-139.txt",
    "question": "Was bedeutet die Abkürzung PMI und wozu dient die PMI-Tabelle?",
    "answer": "Die Abkürzung PMI steht für „Plus“, „Minus“ und „Information“. Die PMI-Tabelle dient zur Entscheidungsvorbereitung und ist eine Visualisierungsvariante in Tabellenform. Sie besteht aus drei großen Feldern, in denen die Vor- und Nachteile einer Entscheidungsoption sowie offene Fragen sortiert werden können. Die Tabelle soll dabei helfen, zwischen mehreren Optionen zu schauen und die Informationsfragen zu konkreten Handlungsschritten zu kommen.",
    "expected": "Die Abkürzung PMI steht für \"Plus\", \"Minus\" und \"Information\". Die PMI-Tabelle ist eine Visualisierungsvariante in Tabellenform zur Entscheidungsvorbereitung, die Vorteile (Plus), Nachteile (Minus) und offene Fragen (Information) gegenüberstellt.",
    "retrieval": [
      {
        "rank": 1,
        "id": "e5100cdcad40359f9757ff1846bb1ad22c026b190a15cd6a3da5e071fbf566ae",
        "score": 0.988938570022583,
        "meta": {
          "file_path": "1001586-136-139.txt",
          "source_id": "971ef64c87ce6eeeeb6a4c0a76df2de0eeb3b6a5e1f7d2045594b018d8f00c67",
          "page_number": 1,
          "split_id": 0,
          "split_idx_start": 0,
          "_split_overlap": [
            {
              "doc_id": "73ddfffb5e1296b06702f140805a42d5d60954264c228c403bbafffe3fbee212",
              "range": [
                0,
                404
              ]
            }
          ]
        },
        "content": "5.5.4 PMI-Tabelle Karin Kress Kurzbeschreibung Die Abkürzung PMI steht für: „Plus“, „Minus“ und „Information“. Es handelt sich um eine Visualisierungsvariante in Tabellenform zur Entscheidungsvor-\nbereitung. Die Tabelle besteht aus drei großen Feldern. Die Gegenüberstel-\nlung von Vorteilen (Plus) und Nachteilen (Minus) wird ergänzt um ein drittes Feld, in das der oder die Ratsuchende offene Fragen eintragen kann. Gearbei-\ntet wird mit mehreren Tabellen. Für jede Handlungsoption wird eine eigene Tabelle angelegt. Diese Visualisierungsvariante kann besonders helfen, wenn der oder die Ratsuchende im Beratungsgespräch zwischen mehreren Optio-\nnen schwankt. Vor allem, wenn der oder die Ratsuchende viel über die jewei-\nligen Nachteile der Entscheidungsoptionen spricht, kann die Methode helfen, über die Informationsfragen zu konkreten Handlungsschritten zu kommen. Phase/Funktion: Anliegen: Material: Zeit: • Ausdruck\n• Stifte Sortieren verschiedener Handlungsoptionen Entscheidungsfindung ab 15"
      },
      {
        "rank": 2,
        "id": "921000c5002d8d269cf6ce1b2a580b143998578efe917a497dbad581ffe3e3cc",
        "score": 0.05114362761378288,
        "meta": {
          "file_path": "1001586-075-102.txt",
          "source_id": "72b5fd5770f54ee865692e906610c146cdb57819fc6177f272c86d8acd555bb1",
          "page_number": 18,
          "split_id": 39,
          "split_idx_start": 43965,
          "_split_overlap": [
            {
              "doc_id": "17713f90eb90a773772330adb0618f2dcf8f6933b56fd125a38a9f34d0c77adc",
              "range": [
                1256,
                1621
              ]
            },
            {
              "doc_id": "2cec7ae456f97002b241badbceec10c6e80e34416adffbda4a4a8250e9971128",
              "range": [
                0,
                406
              ]
            }
          ]
        },
        "content": "dass ihn seine Frau ständig kritisiere, und er ihr deswegen seine in der Beratung gereiften Überlegungen nicht mitteilen wolle. Aus sei-\nner Sicht ist sein Rückzugverhalten in der Partnerschaft die Folge der ständi-\ngen Kritik von Seiten seiner Partnerin. Die Frau ist vermutlich ihrerseits der festen Überzeugung, dass die mangelnde Kommunikationsbereitschaft und „Was meinen der häufige Rückzug ihres Mannes sie unzufrieden machen und ihr kritisches Sie, ist Ihrer Frau wichtig für Ihre gemeinsame Zukunft“\nStreitverhalten erst zur Folge hat. Zum Beispiel über die Frage: gibt der Berater bzw. die Beraterin im geschützten Raum der Beratung dem Ratsuchenden Gelegen- „Wie geht es Ihnen mit diesen Wün-\nheit, sich mit der Kritik der Ehefrau auseinander zu setzen, ohne sich direkt schen Ihrer Partnerin?“\nverteidigen zu müssen. Über die Frage: kann die Beratung sogar dazu verhelfen, ein Gespräch mit der Ehefrau vorzubereiten, um so den Transfer von Beratungsergebnissen in den Alltag des Ratsuchen"
      },
      {
        "rank": 3,
        "id": "73ddfffb5e1296b06702f140805a42d5d60954264c228c403bbafffe3fbee212",
        "score": 0.04779576510190964,
        "meta": {
          "file_path": "1001586-136-139.txt",
          "source_id": "971ef64c87ce6eeeeb6a4c0a76df2de0eeb3b6a5e1f7d2045594b018d8f00c67",
          "page_number": 1,
          "split_id": 1,
          "split_idx_start": 1205,
          "_split_overlap": [
            {
              "doc_id": "e5100cdcad40359f9757ff1846bb1ad22c026b190a15cd6a3da5e071fbf566ae",
              "range": [
                1205,
                1609
              ]
            },
            {
              "doc_id": "a8e2b6a1ea7e7e0040ccb7036118e5b3d58307ec92e7b31d53f2409c3cfc84f5",
              "range": [
                0,
                360
              ]
            }
          ]
        },
        "content": "vor unattrak-\ntiven Tätigkeiten + Orientierung\nNeue Erfahrungen\nNützliches tun\nEngagement macht sich gut im Lebens-\nlauf i: Welche Studienangebote gibt es?\nWie hoch sind die Mieten in meinen Wunschstädten? i: Wie läuft das FSJ ab?\nGehalt/Arbeitszeiten? Abb. 16: PMI-Tabellen (eigene Darstellung) 136 5 Methoden und Techniken\fAblauf der Beratung\nVorbereitung: 1. Die PMI-Tabelle können Sie als Kopie oder Ausdruck bereit- Methode einleiten: legen, oder auf einem A3-Bogen vorzeichnen. 2. Oft ergibt sich innerhalb des Beratungsgesprächs schon eine Situation, in welcher der oder die Ratsuchende über Vor- und Nachteile seiner Handlungsoptionen spricht. In diesem Fall können Sie die Tabelle auch aus einem leeren Blatt heraus entwickeln, indem Sie die ge-\nnannten Stichworte in den drei Abteilungen sortieren. Wenn Sie mit einem Vordruck arbeiten wollen, ist es hilfreich darauf hinzuweisen, dass der oder die Ratsuchende ja bereits einige Vor- und Nachteile genannt hat und die PMI-Tabelle eine Hilfe"
      },
      {
        "rank": 4,
        "id": "e8d4f98b98cec83d018c496a4b5cf95750dfe5d03b9e4d3b1ef28601832df9a0",
        "score": 0.02369462512433529,
        "meta": {
          "file_path": "9783866496811-026-051.txt",
          "source_id": "0ed01db4aa5761f9e7173fd6880d3ef7f1ec44e69cbdde99fa8e51a7cd8dfbd8",
          "page_number": 6,
          "split_id": 9,
          "split_idx_start": 10058,
          "_split_overlap": [
            {
              "doc_id": "f140cc54faa99f12515c920927e22914684d6bfb7088e719020d87410af64fe3",
              "range": [
                1200,
                1582
              ]
            },
            {
              "doc_id": "4fa888d5637681ac54c6b93b7341ee471bf9a6fe7022dbedaff5de00b187613e",
              "range": [
                0,
                400
              ]
            }
          ]
        },
        "content": "auch einen gewissen Raum zur Umsetzung bereitstellte. In der Praxis jedoch fand der Leistungskatalog meist nur gekürzt Anwendung. Kommunikation und auch Dokumentation wurden darin kaum noch beachtet (vgl. Zerbe 1995:27 f). Dieses Instrument der Leistungserfassung wurde nach nur wenigen Jahren offiziell, d.h. bundesweit wieder ausgesetzt, jedoch verwenden manche Krankenhäuser die PPR noch als internes Steuerungsinstrument weiter, um so einen Überblick über den Personalaufwand in der Pflege zu erhalten (vgl. Elsevier 2004:95). Kurze Zeit nach der Entwicklung der PPR wurde 1995 die Pflegeversiche-\nrung eingeführt und es gab die ersten Veränderungsimpulse. 2.1.2. Implementierung der Pflegeversicherung 1995 Im SGB XI dem Pflegeversicherungsgesetz, befinden sich im §§37 und 45 die ersten konkreten Beratungsaufträge für Pflegende. Die Vergütung ist von der zuständigen Pflegekasse zu tragen und die Beratung der Pflegefachkräfte kommt den in eine Pflegestufe eingruppierten pflegebedürftigen Per"
      },
      {
        "rank": 5,
        "id": "ccda36c30aa386e1cf444707d54ebac29d856773b542347194167f786da76d23",
        "score": 0.0022064330987632275,
        "meta": {
          "file_path": "9783839444856-112-221.txt",
          "source_id": "726586a234df23d086c834a96ae0593a72252e939de7473e7450e4d79410e6ec",
          "page_number": 66,
          "split_id": 128,
          "split_idx_start": 153779,
          "_split_overlap": [
            {
              "doc_id": "0a19cca491619edf298690d67496cefe6f5064e9f38e90eac7f245d74ea05617",
              "range": [
                1112,
                1557
              ]
            },
            {
              "doc_id": "37d29bb8b692abfd675ea6405184161a2ceebe8374ca482b9c185f2a60e7f2b2",
              "range": [
                0,
                326
              ]
            }
          ]
        },
        "content": "gesellschaftlichen Bewusstseinsbildung gesehen. Durch die öffentliche Diskussion findet eine Auseinandersetzung mit dem Thema der Anerken-\nnung im Ausland erworbener Qualifikationen statt. Insbesondere durch die Ausweitung des Rechts auf ein Anerkennungsverfahren auch auf Dritt-\nstaatsangehörige wird zudem die Position der Antragsteller_innen gestärkt. »[A]lso es führt prinzipiell dazu, dass es selbstverständlicher wird, davon aus-\nzugehen, dass jemand wirklich eine Qualifikation hat, dass man eine Mög-\f5. Ergebnisse 177 lichkeit findet, diese Qualifikation auch irgendwie zu nutzen, und im Verfah-\nren kann man sich zumindest mal darauf berufen, und es ist auch eigentlich, es ist nicht völlig willkürlich, was wir da jetzt wollen, und eine Zumutung für eine zuständige Stelle, sondern es ist einfach das Recht der Person, einen An-\ntrag zu stellen, und auch eine gewisse Form von Antwort dann zu kriegen« (E/DE, Z. 462-468). Die gestärkte Position der Antragsteller_innen zeigt sich insbesond"
      }
    ]
  },
  {
    "filename": "1001586-136-139.txt",
    "question": "Wie ist die PMI-Tabelle aufgebaut und wie wird sie bei mehreren Handlungsoptionen verwendet?",
    "answer": "Die PMI-Tabelle besteht aus drei großen Feldern, in denen die Vor- und Nachteile einer Handlungsoption sowie offene Fragen aufgeführt werden. Wenn der oder die Ratsuchende mehrere Handlungsoptionen in Betracht zieht, werden für jede Option eine eigene Tabelle erstellt. Die Handlungsoption, von der am meisten Pfeile ausgehen oder auf die die meisten Pfeilspitzen zeigen, wird im Beratungsgespräch als erstes thematisiert. Die Tabelle kann auch dazu verwendet werden, um die Entscheidungsmöglichkeiten zu strukturieren und zu priorisieren. In diesem Fall wird die Frage nachgegangen, auf welche Optionen der oder die Ratsuchende aktiv Einfluss nehmen kann bzw. welchen passiven unveränderbaren Faktoren sie ausgesetzt ist. Die Aufstellung erfolgt in kurz-, mittel- und langfristige Handlungsoptionen.",
    "expected": "Die PMI-Tabelle besteht aus drei großen Feldern: Plus (Vorteile), Minus (Nachteile) und Information (offene Fragen). Für jede Handlungsoption wird eine eigene Tabelle angelegt, sodass mehrere Tabellen genutzt werden, wenn mehrere Optionen zur Auswahl stehen.",
    "retrieval": [
      {
        "rank": 1,
        "id": "e5100cdcad40359f9757ff1846bb1ad22c026b190a15cd6a3da5e071fbf566ae",
        "score": 0.9968528151512146,
        "meta": {
          "file_path": "1001586-136-139.txt",
          "source_id": "971ef64c87ce6eeeeb6a4c0a76df2de0eeb3b6a5e1f7d2045594b018d8f00c67",
          "page_number": 1,
          "split_id": 0,
          "split_idx_start": 0,
          "_split_overlap": [
            {
              "doc_id": "73ddfffb5e1296b06702f140805a42d5d60954264c228c403bbafffe3fbee212",
              "range": [
                0,
                404
              ]
            }
          ]
        },
        "content": "5.5.4 PMI-Tabelle Karin Kress Kurzbeschreibung Die Abkürzung PMI steht für: „Plus“, „Minus“ und „Information“. Es handelt sich um eine Visualisierungsvariante in Tabellenform zur Entscheidungsvor-\nbereitung. Die Tabelle besteht aus drei großen Feldern. Die Gegenüberstel-\nlung von Vorteilen (Plus) und Nachteilen (Minus) wird ergänzt um ein drittes Feld, in das der oder die Ratsuchende offene Fragen eintragen kann. Gearbei-\ntet wird mit mehreren Tabellen. Für jede Handlungsoption wird eine eigene Tabelle angelegt. Diese Visualisierungsvariante kann besonders helfen, wenn der oder die Ratsuchende im Beratungsgespräch zwischen mehreren Optio-\nnen schwankt. Vor allem, wenn der oder die Ratsuchende viel über die jewei-\nligen Nachteile der Entscheidungsoptionen spricht, kann die Methode helfen, über die Informationsfragen zu konkreten Handlungsschritten zu kommen. Phase/Funktion: Anliegen: Material: Zeit: • Ausdruck\n• Stifte Sortieren verschiedener Handlungsoptionen Entscheidungsfindung ab 15"
      },
      {
        "rank": 2,
        "id": "73ddfffb5e1296b06702f140805a42d5d60954264c228c403bbafffe3fbee212",
        "score": 0.9948651194572449,
        "meta": {
          "file_path": "1001586-136-139.txt",
          "source_id": "971ef64c87ce6eeeeb6a4c0a76df2de0eeb3b6a5e1f7d2045594b018d8f00c67",
          "page_number": 1,
          "split_id": 1,
          "split_idx_start": 1205,
          "_split_overlap": [
            {
              "doc_id": "e5100cdcad40359f9757ff1846bb1ad22c026b190a15cd6a3da5e071fbf566ae",
              "range": [
                1205,
                1609
              ]
            },
            {
              "doc_id": "a8e2b6a1ea7e7e0040ccb7036118e5b3d58307ec92e7b31d53f2409c3cfc84f5",
              "range": [
                0,
                360
              ]
            }
          ]
        },
        "content": "vor unattrak-\ntiven Tätigkeiten + Orientierung\nNeue Erfahrungen\nNützliches tun\nEngagement macht sich gut im Lebens-\nlauf i: Welche Studienangebote gibt es?\nWie hoch sind die Mieten in meinen Wunschstädten? i: Wie läuft das FSJ ab?\nGehalt/Arbeitszeiten? Abb. 16: PMI-Tabellen (eigene Darstellung) 136 5 Methoden und Techniken\fAblauf der Beratung\nVorbereitung: 1. Die PMI-Tabelle können Sie als Kopie oder Ausdruck bereit- Methode einleiten: legen, oder auf einem A3-Bogen vorzeichnen. 2. Oft ergibt sich innerhalb des Beratungsgesprächs schon eine Situation, in welcher der oder die Ratsuchende über Vor- und Nachteile seiner Handlungsoptionen spricht. In diesem Fall können Sie die Tabelle auch aus einem leeren Blatt heraus entwickeln, indem Sie die ge-\nnannten Stichworte in den drei Abteilungen sortieren. Wenn Sie mit einem Vordruck arbeiten wollen, ist es hilfreich darauf hinzuweisen, dass der oder die Ratsuchende ja bereits einige Vor- und Nachteile genannt hat und die PMI-Tabelle eine Hilfe"
      },
      {
        "rank": 3,
        "id": "8a13870c1e138251f72d2031f0a81d979276472cb1de16160c4456786e65275a",
        "score": 0.9848424196243286,
        "meta": {
          "file_path": "1001586-136-139.txt",
          "source_id": "971ef64c87ce6eeeeb6a4c0a76df2de0eeb3b6a5e1f7d2045594b018d8f00c67",
          "page_number": 3,
          "split_id": 4,
          "split_idx_start": 4428,
          "_split_overlap": [
            {
              "doc_id": "8442627039a0208851a6c3ad9c5c6aced010eea0cdb736bcb471b17733c0e4b1",
              "range": [
                1076,
                1466
              ]
            },
            {
              "doc_id": "eb6f9afa2afb4615e0d3af63e14efca3bd6beb5ab8965d6c9fd6875d659b402d",
              "range": [
                0,
                368
              ]
            }
          ]
        },
        "content": "Tabelle dem oder der Ratsuchenden auch unausge-\nfüllt als Anregung für eigene weitere Überlegungen mitgeben. Bei mehreren Beratungssitzungen kann das Anlegen der Tabelle zur Vorbereitung auf ein nächstes Gespräch dienen.\nKommentar zum Einsatz\nZielgruppe: Die Methode lässt sich, wenn Sie die Tabelle für die ratsuchende Person ausfüllen, auf viele Personenkreise anwenden. Für Ratsuchende, die selbst schon sehr strukturiert vorgehen, reicht es mitunter, das Modell zur Anliegen: Eigenbearbeitung vorzustellen. Entscheidungsvorbereitung zu verschiedenen Weiterbildungen, zwischen Weiterbildung oder beruflicher Umorientierung, zwischen privaten und beruflichen Prioritäten, zwischen zeitlich unterschiedlich umfangreichen Phase im Beratungsgespräch:\nOptionen. Das Beratungsgespräch sollte schon so weit fortgeschritten sein, dass sich auch verschiedene Entscheidungsvarianten abzeichnen. Die Methode ist daher eher am Ende der Mittelphase anzusie-\ndeln. Ergeben sich aus der Methode jedoch neue Frage"
      },
      {
        "rank": 4,
        "id": "0be37502d3ab5747b57674140453667f9d05ad018c9bb0d0796df4c28baad9ce",
        "score": 0.9439444541931152,
        "meta": {
          "file_path": "1001586-162-166.txt",
          "source_id": "20f2d2defc90565713f4374cbb91f111d67b34e9ec904032a8ed20542f934de1",
          "page_number": 1,
          "split_id": 1,
          "split_idx_start": 1278,
          "_split_overlap": [
            {
              "doc_id": "8b9d39cf093c92480fe3fb64bf180fb8b86f8a1c8aff5b78a451b3781775c83c",
              "range": [
                1278,
                1658
              ]
            },
            {
              "doc_id": "af1bb4809e111f5e3b9f083cd83352a18a8f65c2ed7da1142838a2e71242fc85",
              "range": [
                0,
                388
              ]
            }
          ]
        },
        "content": "Handlungsoptionen zueinander durch Pfeile und Symbole dargestellt. Die Handlungsoption, von der am meisten Pfeile ausgehen oder auf die die meisten Pfeilspitzen zeigen, wird im Bera-\ntungsgespräch als erstes thematisiert.\n162 5 Methoden und Techniken\fIm Anschluss an die Netzwerkmethode wird entweder gemeinsam, oder von der ratsuchenden Person alleine als Aufgabe zu Hause, eine Hand-\nlungs-Matrix ausgefüllt. In dieser Matrix werden die Entscheidungsmöglich-\nkeiten strukturiert und priorisiert. Dann wird der Frage nachgegangen, auf welche Optionen der oder die Ratsuchende aktiv Einfluss nehmen kann bzw. welchen passiven unveränderbaren Faktoren sie ausgesetzt ist. Die Aufstel-\nlung erfolgt in kurz-, mittel- und langfristige Handlungsoptionen. Phase/Funktion: Anliegen: Material: Zeit: • Flipchart\n• Stifte\n• Matrix als Kopie Mittel- und Endphase: Optionen ordnen, abwä-\ngen und priorisieren Entscheidungsfindung und Priorisieren von Handlungsoptionen ab 45 Min. Ablauf der Beratung\nVorbereitu"
      },
      {
        "rank": 5,
        "id": "e69eaf522c287e2073314429dccd8199270e421bacfe3c942fdca6dae6def7bf",
        "score": 0.9267672896385193,
        "meta": {
          "file_path": "HiBiFo_2019_1_Obermoser_Beraten_und_Diagnostizieren.txt",
          "source_id": "8129490997f07cf0df6cee42a671cd0ff9bc7c73eb13cc5d0aec0a7bd94f79f8",
          "page_number": 6,
          "split_id": 5,
          "split_idx_start": 7051,
          "_split_overlap": [
            {
              "doc_id": "02d2c93b0da737975743b82944511c080f3b0a11ba66ffe43c5543587cc671cb",
              "range": [
                1313,
                1777
              ]
            },
            {
              "doc_id": "39f5d1111d8d520d3badfaa0f420fdcaa71238c6cc3f76cd5ac5b39a18539b42",
              "range": [
                0,
                427
              ]
            }
          ]
        },
        "content": "in Tabelle 1 dargestellt: Im Aufgabenfeld Lernbegleitung erfüllen Lehrende alle pädagogischen Funktionen von Schule (Qualifikation, Personalisation, Sozialisation, Enkulturation), nur nicht die selektive Aufgabe der summativen Beurteilung (Perkhofer-Czapek & Potzmann, 2016). Rollenbilder als Bündel normativer, situationsspezifisch sinnvoller Verhaltens-\nerwartungen sind jedoch immer einem historischen und kulturellen Wandel unter-\nworfen und variieren auch in Abhängigkeit der Erwartungen der Bezugsgruppen (Tab. 1). Tab. 1: Erwartungshaltung ausgewählter Bezugsgruppen und das entsprechende Rollenbild bzw. Handlungsfeld im Lehrberuf (Perkhofer-Czapek & Potzmann, 2016, S. 30) Erwartungen der Bezugsgruppen Rollenbild Handlungsfeld Schüler/in Wissensvermittlung Fachexpertin/-experte, Lehrende/r Lehren, Informieren Beratung Hilfe Orientierung, Führung Berater/in, Coach Helfer/in, Tutor/in Modell, Vorbild, Mentor/in Beraten Helfen Erziehen Eltern Beziehung Freund/in, Vertraute/r Kooperieren W"
      }
    ]
  },
  {
    "filename": "1001586-136-139.txt",
    "question": "Wie kann die PMI-Tabelle im Beratungsgespräch eingesetzt werden, wenn der Ratsuchende hauptsächlich über Nachteile einer Option spricht?",
    "answer": "Wenn der Ratsuchende hauptsächlich über Nachteile einer Option spricht, kann die PMI-Tabelle helfen, über die Informationsfragen zu konkreten Handlungsschritten zu kommen. In diesem Fall kann die Tabelle entwickelt werden, indem die genannten Stichworte in den drei Abteilungen sortiert werden. Der Berater sollte den Aufbau der Tabelle kurz erklären und darauf hinweisen, dass der oder die Ratsuchende das ausgefüllte Ergebnis mit nach Hause nehmen kann. Dies kann dazu beitragen, dass der Ratsuchende konkrete Handlungsschritte plant und sich auf eine Entscheidung einlässt.",
    "expected": "Wenn der Ratsuchende vor allem über Nachteile spricht, kann die PMI-Tabelle helfen, indem im Informationsfeld offene Fragen gesammelt werden, die dann zu konkreten Handlungsschritten führen. So wird der Fokus erweitert und eine ausgewogenere Entscheidungsbasis geschaffen.",
    "retrieval": [
      {
        "rank": 1,
        "id": "e5100cdcad40359f9757ff1846bb1ad22c026b190a15cd6a3da5e071fbf566ae",
        "score": 0.9974931478500366,
        "meta": {
          "file_path": "1001586-136-139.txt",
          "source_id": "971ef64c87ce6eeeeb6a4c0a76df2de0eeb3b6a5e1f7d2045594b018d8f00c67",
          "page_number": 1,
          "split_id": 0,
          "split_idx_start": 0,
          "_split_overlap": [
            {
              "doc_id": "73ddfffb5e1296b06702f140805a42d5d60954264c228c403bbafffe3fbee212",
              "range": [
                0,
                404
              ]
            }
          ]
        },
        "content": "5.5.4 PMI-Tabelle Karin Kress Kurzbeschreibung Die Abkürzung PMI steht für: „Plus“, „Minus“ und „Information“. Es handelt sich um eine Visualisierungsvariante in Tabellenform zur Entscheidungsvor-\nbereitung. Die Tabelle besteht aus drei großen Feldern. Die Gegenüberstel-\nlung von Vorteilen (Plus) und Nachteilen (Minus) wird ergänzt um ein drittes Feld, in das der oder die Ratsuchende offene Fragen eintragen kann. Gearbei-\ntet wird mit mehreren Tabellen. Für jede Handlungsoption wird eine eigene Tabelle angelegt. Diese Visualisierungsvariante kann besonders helfen, wenn der oder die Ratsuchende im Beratungsgespräch zwischen mehreren Optio-\nnen schwankt. Vor allem, wenn der oder die Ratsuchende viel über die jewei-\nligen Nachteile der Entscheidungsoptionen spricht, kann die Methode helfen, über die Informationsfragen zu konkreten Handlungsschritten zu kommen. Phase/Funktion: Anliegen: Material: Zeit: • Ausdruck\n• Stifte Sortieren verschiedener Handlungsoptionen Entscheidungsfindung ab 15"
      },
      {
        "rank": 2,
        "id": "8a13870c1e138251f72d2031f0a81d979276472cb1de16160c4456786e65275a",
        "score": 0.9965938925743103,
        "meta": {
          "file_path": "1001586-136-139.txt",
          "source_id": "971ef64c87ce6eeeeb6a4c0a76df2de0eeb3b6a5e1f7d2045594b018d8f00c67",
          "page_number": 3,
          "split_id": 4,
          "split_idx_start": 4428,
          "_split_overlap": [
            {
              "doc_id": "8442627039a0208851a6c3ad9c5c6aced010eea0cdb736bcb471b17733c0e4b1",
              "range": [
                1076,
                1466
              ]
            },
            {
              "doc_id": "eb6f9afa2afb4615e0d3af63e14efca3bd6beb5ab8965d6c9fd6875d659b402d",
              "range": [
                0,
                368
              ]
            }
          ]
        },
        "content": "Tabelle dem oder der Ratsuchenden auch unausge-\nfüllt als Anregung für eigene weitere Überlegungen mitgeben. Bei mehreren Beratungssitzungen kann das Anlegen der Tabelle zur Vorbereitung auf ein nächstes Gespräch dienen.\nKommentar zum Einsatz\nZielgruppe: Die Methode lässt sich, wenn Sie die Tabelle für die ratsuchende Person ausfüllen, auf viele Personenkreise anwenden. Für Ratsuchende, die selbst schon sehr strukturiert vorgehen, reicht es mitunter, das Modell zur Anliegen: Eigenbearbeitung vorzustellen. Entscheidungsvorbereitung zu verschiedenen Weiterbildungen, zwischen Weiterbildung oder beruflicher Umorientierung, zwischen privaten und beruflichen Prioritäten, zwischen zeitlich unterschiedlich umfangreichen Phase im Beratungsgespräch:\nOptionen. Das Beratungsgespräch sollte schon so weit fortgeschritten sein, dass sich auch verschiedene Entscheidungsvarianten abzeichnen. Die Methode ist daher eher am Ende der Mittelphase anzusie-\ndeln. Ergeben sich aus der Methode jedoch neue Frage"
      },
      {
        "rank": 3,
        "id": "73ddfffb5e1296b06702f140805a42d5d60954264c228c403bbafffe3fbee212",
        "score": 0.9926555156707764,
        "meta": {
          "file_path": "1001586-136-139.txt",
          "source_id": "971ef64c87ce6eeeeb6a4c0a76df2de0eeb3b6a5e1f7d2045594b018d8f00c67",
          "page_number": 1,
          "split_id": 1,
          "split_idx_start": 1205,
          "_split_overlap": [
            {
              "doc_id": "e5100cdcad40359f9757ff1846bb1ad22c026b190a15cd6a3da5e071fbf566ae",
              "range": [
                1205,
                1609
              ]
            },
            {
              "doc_id": "a8e2b6a1ea7e7e0040ccb7036118e5b3d58307ec92e7b31d53f2409c3cfc84f5",
              "range": [
                0,
                360
              ]
            }
          ]
        },
        "content": "vor unattrak-\ntiven Tätigkeiten + Orientierung\nNeue Erfahrungen\nNützliches tun\nEngagement macht sich gut im Lebens-\nlauf i: Welche Studienangebote gibt es?\nWie hoch sind die Mieten in meinen Wunschstädten? i: Wie läuft das FSJ ab?\nGehalt/Arbeitszeiten? Abb. 16: PMI-Tabellen (eigene Darstellung) 136 5 Methoden und Techniken\fAblauf der Beratung\nVorbereitung: 1. Die PMI-Tabelle können Sie als Kopie oder Ausdruck bereit- Methode einleiten: legen, oder auf einem A3-Bogen vorzeichnen. 2. Oft ergibt sich innerhalb des Beratungsgesprächs schon eine Situation, in welcher der oder die Ratsuchende über Vor- und Nachteile seiner Handlungsoptionen spricht. In diesem Fall können Sie die Tabelle auch aus einem leeren Blatt heraus entwickeln, indem Sie die ge-\nnannten Stichworte in den drei Abteilungen sortieren. Wenn Sie mit einem Vordruck arbeiten wollen, ist es hilfreich darauf hinzuweisen, dass der oder die Ratsuchende ja bereits einige Vor- und Nachteile genannt hat und die PMI-Tabelle eine Hilfe"
      },
      {
        "rank": 4,
        "id": "25727b7cb1068bb4a63e5277653974f5f38f8e73820b756b8290102feb2e557d",
        "score": 0.9638867378234863,
        "meta": {
          "file_path": "1001586-191-206.txt",
          "source_id": "5996317b3d6fb495232e6fedeb0c860a654108106958d08f3a09b9eb5dd0c419",
          "page_number": 6,
          "split_id": 13,
          "split_idx_start": 14576,
          "_split_overlap": [
            {
              "doc_id": "962b8115179b97759b149ab712a32e94fcd626d0a7549757f6f1f8a8dd6bdb5b",
              "range": [
                1135,
                1532
              ]
            },
            {
              "doc_id": "9677d428fe916b5e39d3c0a02f6600849daeb4d0be29249aa15411a29c9f24fa",
              "range": [
                0,
                409
              ]
            }
          ]
        },
        "content": "diese – zwischen den Me-\nthoden – zum impliziten oder expliziten Gesprächsgegenstand gemacht wer-\nden: Welche wiederkehrenden Handlungsstrategien der Ratsuchenden sind im Kontakt mit der Beraterin oder dem Berater erkennbar? Dies ist bspw. eine der reflexiven Fragen der kommunikativen Metaebene, die Beziehungs-\nhandeln transparenter machen und dem oder der Ratsuchenden Aufschluss darüber geben kann, welche Verhaltensmuster sie auch in andere Beziehun-\ngen trägt und umgekehrt. Bemerke ich z.B., dass der oder die Ratsuchende denn?“, kann ich während der Beratung immer wieder fragt: „Was meinen diese Beobachtung dem Ratsuchenden zur Verfügung stellen. Prozessorientierung versus Ergebnisorientierung Sie Das Erleben einer professionell sicheren Beziehung zum Berater trägt – im besten Fall – also dazu bei, dass wiederkehrende Muster oder erstarrte Denk-\nformen beim Ratsuchenden wieder in Bewegung kommen und damit ver-\nändert werden können. Dies kann sogar bewirken, dass Ratsuchende in der Bi"
      },
      {
        "rank": 5,
        "id": "da4b5b3b5f94cf7e78995dc81aa63ed0bb9d64e48768ced7de5684404d8da76e",
        "score": 0.9545062780380249,
        "meta": {
          "file_path": "1001586-103-122.txt",
          "source_id": "703de242bbca21fb44a372f294b8d15e12e6513559c5c63aeb11c6ab02234406",
          "page_number": 8,
          "split_id": 17,
          "split_idx_start": 19292,
          "_split_overlap": [
            {
              "doc_id": "2f84dda1d846ff4f5acd4ff12f5691be297682caf0000093558dc72551b51e96",
              "range": [
                1052,
                1408
              ]
            },
            {
              "doc_id": "9e8f7bfabe997d47205520acb7b6bb30b7f1f773f20eb20760891b67d005cc90",
              "range": [
                0,
                338
              ]
            }
          ]
        },
        "content": "Ratsuchende eine Begründung, warum es sinn-\nvoll ist, sich auf einen Wechsel der Handlungs- oder Medienform einzulassen. Diese Begründung darf jedoch auch nicht zu „technisch“ ausfallen, da sich der bzw. die Ratsuchende ja in gedanklicher Auseinandersetzung mit seinem An-\nliegen befindet. Dies wiederum hat den Vorteil, dass sich Ratsuchende in der Regel wenig mit den Details einer Methode beschäftigen. Wenn sie das Ziel und die grobe Struktur nachvollziehen können und als stimmig mit ihrem An-\nliegen erleben, ist die Chance groß, dass sie sich auf das Verfahren auch einlas-\nsen. Der oder die Beraterin kann diesen Einführungsprozess unterschiedlich gestalten.\nEinführungsvariante I: Eine Methode aus dem Beratungsprozess heraus entwickeln In dieser Variante stelle ich die Methode nicht in allen Einzelheiten vor. Aus Sicht des oder der Ratsuchenden entwickle ich die Methode aus unserem Ge-\nspräch heraus. Ich selbst habe die grobe Struktur jedoch im Kopf und weiß, welche Bausteine im Prozes"
      }
    ]
  },
  {
    "filename": "1001586-136-139.txt",
    "question": "Welche kritischen Aspekte sollten bei der Nutzung der PMI-Tabelle im Beratungsgespräch beachtet werden, insbesondere im Hinblick auf die Auswahl der Handlungsoptionen?",
    "answer": "Die PMI-Tabelle kann eine nützliche Hilfestellung im Beratungsgespräch sein, um die Vor- und Nachteile verschiedener Handlungsoptionen zu visualisieren und offene Fragen zu klären. Wenn jedoch die Ratsuchenden mehr oder weniger aufgeschlossen sind, kann die Frage nach den Handlungsoptionen zu einem Zwischenstand führen, an dem die Ratsuchenden noch nicht sicher sind. In diesem Fall sollte der Berater oder die Beraterin darauf hinweisen, dass die PMI-Tabelle eine Hilfestellung zur Visualisierung liefert, und den Aufbau der Tabelle kurz erklären. Es ist auch wichtig, darauf hinzuweisen, dass die Ratsuchenden das ausgefüllte Ergebnis mit nach Hause nehmen können, um weitere Überlegungen anzustellen. Außerdem ist es ratsam, auf die möglichen Grenzen und Herausforderungen innerhalb der Beratungsbeziehung einzugehen, insbesondere wenn die Ratsuchenden durch andere Stellen zur Beratung „geschickt“ oder verpflichtet werden. Es kann auch dazu führen, dass die Ratsuchenden nicht in der Lage sind, die Handlungsoptionen aus freier Wahl zu wählen, sondern vielmehr von ihren Umständen bestimmt werden. In diesem Fall sollte der Berater oder die Beraterin die Ratsuchenden unterstützen und ihnen helfen, ihre Motivationen und Ziele zu klären. Die PMI-Tabelle kann in diesem Fall als Hilfestellung zur Identifizierung der möglichen Handlungsoptionen und ihrer Vor- und Nachteile dienen.",
    "expected": "Ein kritischer Aspekt ist, dass Ratsuchende sich oft an Optionen orientieren, die als akzeptabel von anderen gelten, was die Auswahl einschränken kann. Außerdem sollte der Berater darauf achten, dass die PMI-Tabelle nicht nur Vor- und Nachteile sichtbar macht, sondern auch offene Fragen klärt, um vorschnelle oder einseitige Entscheidungen zu vermeiden.",
    "retrieval": [
      {
        "rank": 1,
        "id": "e5100cdcad40359f9757ff1846bb1ad22c026b190a15cd6a3da5e071fbf566ae",
        "score": 0.9056682586669922,
        "meta": {
          "file_path": "1001586-136-139.txt",
          "source_id": "971ef64c87ce6eeeeb6a4c0a76df2de0eeb3b6a5e1f7d2045594b018d8f00c67",
          "page_number": 1,
          "split_id": 0,
          "split_idx_start": 0,
          "_split_overlap": [
            {
              "doc_id": "73ddfffb5e1296b06702f140805a42d5d60954264c228c403bbafffe3fbee212",
              "range": [
                0,
                404
              ]
            }
          ]
        },
        "content": "5.5.4 PMI-Tabelle Karin Kress Kurzbeschreibung Die Abkürzung PMI steht für: „Plus“, „Minus“ und „Information“. Es handelt sich um eine Visualisierungsvariante in Tabellenform zur Entscheidungsvor-\nbereitung. Die Tabelle besteht aus drei großen Feldern. Die Gegenüberstel-\nlung von Vorteilen (Plus) und Nachteilen (Minus) wird ergänzt um ein drittes Feld, in das der oder die Ratsuchende offene Fragen eintragen kann. Gearbei-\ntet wird mit mehreren Tabellen. Für jede Handlungsoption wird eine eigene Tabelle angelegt. Diese Visualisierungsvariante kann besonders helfen, wenn der oder die Ratsuchende im Beratungsgespräch zwischen mehreren Optio-\nnen schwankt. Vor allem, wenn der oder die Ratsuchende viel über die jewei-\nligen Nachteile der Entscheidungsoptionen spricht, kann die Methode helfen, über die Informationsfragen zu konkreten Handlungsschritten zu kommen. Phase/Funktion: Anliegen: Material: Zeit: • Ausdruck\n• Stifte Sortieren verschiedener Handlungsoptionen Entscheidungsfindung ab 15"
      },
      {
        "rank": 2,
        "id": "73ddfffb5e1296b06702f140805a42d5d60954264c228c403bbafffe3fbee212",
        "score": 0.8831683993339539,
        "meta": {
          "file_path": "1001586-136-139.txt",
          "source_id": "971ef64c87ce6eeeeb6a4c0a76df2de0eeb3b6a5e1f7d2045594b018d8f00c67",
          "page_number": 1,
          "split_id": 1,
          "split_idx_start": 1205,
          "_split_overlap": [
            {
              "doc_id": "e5100cdcad40359f9757ff1846bb1ad22c026b190a15cd6a3da5e071fbf566ae",
              "range": [
                1205,
                1609
              ]
            },
            {
              "doc_id": "a8e2b6a1ea7e7e0040ccb7036118e5b3d58307ec92e7b31d53f2409c3cfc84f5",
              "range": [
                0,
                360
              ]
            }
          ]
        },
        "content": "vor unattrak-\ntiven Tätigkeiten + Orientierung\nNeue Erfahrungen\nNützliches tun\nEngagement macht sich gut im Lebens-\nlauf i: Welche Studienangebote gibt es?\nWie hoch sind die Mieten in meinen Wunschstädten? i: Wie läuft das FSJ ab?\nGehalt/Arbeitszeiten? Abb. 16: PMI-Tabellen (eigene Darstellung) 136 5 Methoden und Techniken\fAblauf der Beratung\nVorbereitung: 1. Die PMI-Tabelle können Sie als Kopie oder Ausdruck bereit- Methode einleiten: legen, oder auf einem A3-Bogen vorzeichnen. 2. Oft ergibt sich innerhalb des Beratungsgesprächs schon eine Situation, in welcher der oder die Ratsuchende über Vor- und Nachteile seiner Handlungsoptionen spricht. In diesem Fall können Sie die Tabelle auch aus einem leeren Blatt heraus entwickeln, indem Sie die ge-\nnannten Stichworte in den drei Abteilungen sortieren. Wenn Sie mit einem Vordruck arbeiten wollen, ist es hilfreich darauf hinzuweisen, dass der oder die Ratsuchende ja bereits einige Vor- und Nachteile genannt hat und die PMI-Tabelle eine Hilfe"
      },
      {
        "rank": 3,
        "id": "0f3d416f4696f945891756b6251d8f5a72c915ba30127e7b99ac4b5c72441a93",
        "score": 0.8415558934211731,
        "meta": {
          "file_path": "9783839444856-112-221.txt",
          "source_id": "726586a234df23d086c834a96ae0593a72252e939de7473e7450e4d79410e6ec",
          "page_number": 108,
          "split_id": 211,
          "split_idx_start": 251074,
          "_split_overlap": [
            {
              "doc_id": "a71622c7ccf62816cd8a7fff68cddc81b7dc3ccac574cd824ad089f0a55a0665",
              "range": [
                1379,
                1996
              ]
            },
            {
              "doc_id": "e165f1b553deb18588982cfd602f6f19fd5489d0cf23020916de1d5f9136fd33",
              "range": [
                0,
                511
              ]
            }
          ]
        },
        "content": "Beratung Zielsetzung individuelle Ebene strukturelle Ebene individuelle/\nstrukturelle Ebene Handlungsstrategien Empowerment, Weitervermittlungen Ausgleich struktureller Defizite strukturelle\nEinwirkungen Selbstverständnis spezialisierte\nFachberatung parteiliche\nFachberatung unabhängige Fachberatung Quelle: eigene Darstellung 5.4.4 Zusammenfassung: (Aus-)Handlungsmuster zwischen Handlungs- und Anerkennungsebene In den ersten beiden Zugängen zu Aushandlungsprozessen werden jeweils die beschriebenen beratungstheoretischen Zugänge eines emanzipativen Beratungsverständnisses und einer parteilichen Beratungshaltung deutlich. Aus einer beratungstheoretischen Perspektive kann der erste Handlungs-\nzugang eher einem pädagogischen Beratungsverständnis zugeordnet wer-\nden, während der zweite Zugang tendenziell dem Beratungsverständnis in der Sozialen Arbeit entspricht. In Bezug auf die Beratungshaltung kann der dritte Zugang als Kombination aus den ersten beiden Zugängen verstanden werden. In der "
      },
      {
        "rank": 4,
        "id": "e9ccc990f86e1f944e2d91cf9be962c84bcf20e74730391b26aa4c01149057ea",
        "score": 0.338817834854126,
        "meta": {
          "file_path": "1001586-039-074.txt",
          "source_id": "f93a356287fbee599a6282971f7556b0781cb19f067f935a25a58e8a75d62d81",
          "page_number": 16,
          "split_id": 40,
          "split_idx_start": 45696,
          "_split_overlap": [
            {
              "doc_id": "1f79d921120f65405fcfa7be8014858c1972816e5898e7254d82302f023292a3",
              "range": [
                1063,
                1439
              ]
            },
            {
              "doc_id": "82a7bd9b729438e156de3f6de41774117ac0a05a495261eea91b00e32cc5b9f6",
              "range": [
                0,
                361
              ]
            }
          ]
        },
        "content": "kann dazu führen, dass die Ratsuchenden mit einem positiven Blick in die Zukunft aus dem Beratungsprozess aussteigen können und klar wird, dass der Berater bzw. die Beraterin Zutrauen in die nächsten Schritte des Ratsuchenden hat. 54 3 Erfahrungsraum Beratung: Handlungsorientierung\fGute Beziehungsarbeit innerhalb der Beratung bedeutet also, sich von einem Beziehungsaufbau, über die kontinuierliche Aktualisierung der Bezie-\nhung bis hin zur Beendigung derselben Gedanken zu machen, und diese indi-\nviduell reflektiert auch mit Hilfe von Methoden und Techniken in Handlung umzusetzen.\nGrenzen und Herausforderungen innerhalb der Beratungsbeziehung – kritische Reflexion Beziehungsarbeit innerhalb der Bildungsberatung ist voraussetzungsvoll und daher nicht immer so umsetzbar, wie es idealtypisch sinnvoll und förderlich für die Beratungspraxis wäre. Dazu gehört beispielsweise der Umstand, dass innerhalb der Erwachse-\nnenbildung nicht immer alle Ratsuchenden zu den klassischen Ratsuchenden gehör"
      },
      {
        "rank": 5,
        "id": "e69eaf522c287e2073314429dccd8199270e421bacfe3c942fdca6dae6def7bf",
        "score": 0.29226920008659363,
        "meta": {
          "file_path": "HiBiFo_2019_1_Obermoser_Beraten_und_Diagnostizieren.txt",
          "source_id": "8129490997f07cf0df6cee42a671cd0ff9bc7c73eb13cc5d0aec0a7bd94f79f8",
          "page_number": 6,
          "split_id": 5,
          "split_idx_start": 7051,
          "_split_overlap": [
            {
              "doc_id": "02d2c93b0da737975743b82944511c080f3b0a11ba66ffe43c5543587cc671cb",
              "range": [
                1313,
                1777
              ]
            },
            {
              "doc_id": "39f5d1111d8d520d3badfaa0f420fdcaa71238c6cc3f76cd5ac5b39a18539b42",
              "range": [
                0,
                427
              ]
            }
          ]
        },
        "content": "in Tabelle 1 dargestellt: Im Aufgabenfeld Lernbegleitung erfüllen Lehrende alle pädagogischen Funktionen von Schule (Qualifikation, Personalisation, Sozialisation, Enkulturation), nur nicht die selektive Aufgabe der summativen Beurteilung (Perkhofer-Czapek & Potzmann, 2016). Rollenbilder als Bündel normativer, situationsspezifisch sinnvoller Verhaltens-\nerwartungen sind jedoch immer einem historischen und kulturellen Wandel unter-\nworfen und variieren auch in Abhängigkeit der Erwartungen der Bezugsgruppen (Tab. 1). Tab. 1: Erwartungshaltung ausgewählter Bezugsgruppen und das entsprechende Rollenbild bzw. Handlungsfeld im Lehrberuf (Perkhofer-Czapek & Potzmann, 2016, S. 30) Erwartungen der Bezugsgruppen Rollenbild Handlungsfeld Schüler/in Wissensvermittlung Fachexpertin/-experte, Lehrende/r Lehren, Informieren Beratung Hilfe Orientierung, Führung Berater/in, Coach Helfer/in, Tutor/in Modell, Vorbild, Mentor/in Beraten Helfen Erziehen Eltern Beziehung Freund/in, Vertraute/r Kooperieren W"
      }
    ]
  },
  {
    "filename": "1001586-136-139.txt",
    "question": "Wie kann die PMI-Tabelle dazu beitragen, dass Ratsuchende zwischen mehreren Optionen eine fundierte Entscheidung treffen, und welche Rolle spielen dabei die drei Felder der Tabelle?",
    "answer": "Die PMI-Tabelle kann dazu beitragen, dass Ratsuchende zwischen mehreren Optionen eine fundierte Entscheidung treffen, indem sie die Vor- und Nachteile der Optionen visuell darstellt und die Ratsuchenden dazu anregt, ihre Fragen und Bedenken zu formulieren. Die drei Felder der Tabelle - \"Plus\", \"Minus\" und \"Information\" - ermöglichen es den Ratsuchenden, ihre Vorteile und Nachteile zu priorisieren und ihre offenen Fragen zu klären. Durch die Visualisierung der Optionen kann die PMI-Tabelle helfen, dass die Ratsuchenden eine fundierte Entscheidung treffen und nicht durch emotionale oder unklare Überlegungen beeinflusst werden.\n        Die drei Felder der Tabelle können wie folgt verwendet werden:\n        - \"Plus\" : In diesem Feld können die Vorteile der Optionen aufgeführt werden, wie zum Beispiel Vorteile der Entscheidung, wie z.B. eine bessere Karrierechance oder ein höheres Einkommen.\n        - \"Minus\" : In diesem Feld können die Nachteile der Optionen aufgeführt werden, wie zum Beispiel Nachteile der Entscheidung, wie z.B. ein höherer Stress oder eine längere Arbeitszeit.\n        - \"Information\" : In diesem Feld können die offenen Fragen und Bedenken der Ratsuchenden aufgeführt werden, wie zum Beispiel Fragen zu den möglichen Folgen der Entscheidung oder Bedenken über die möglichen Risiken.\n        Durch die Verwendung der PMI-Tabelle können Ratsuchende ihre Optionen sorgfältig abwägen und eine fundierte Entscheidung treffen, die auf ihren Bedürfnissen und Zielen basiert.",
    "expected": "Die PMI-Tabelle unterstützt Ratsuchende, indem sie Vorteile (Plus) und Nachteile (Minus) jeder Option übersichtlich darstellt, wodurch eine klare Gegenüberstellung entsteht. Das Informationsfeld ermöglicht es, offene Fragen zu sammeln, die noch geklärt werden müssen. Zusammen helfen diese drei Felder, eine differenzierte Sicht auf jede Option zu bekommen und so eine fundierte Entscheidung zu ermöglichen.",
    "retrieval": [
      {
        "rank": 1,
        "id": "e5100cdcad40359f9757ff1846bb1ad22c026b190a15cd6a3da5e071fbf566ae",
        "score": 0.9942460656166077,
        "meta": {
          "file_path": "1001586-136-139.txt",
          "source_id": "971ef64c87ce6eeeeb6a4c0a76df2de0eeb3b6a5e1f7d2045594b018d8f00c67",
          "page_number": 1,
          "split_id": 0,
          "split_idx_start": 0,
          "_split_overlap": [
            {
              "doc_id": "73ddfffb5e1296b06702f140805a42d5d60954264c228c403bbafffe3fbee212",
              "range": [
                0,
                404
              ]
            }
          ]
        },
        "content": "5.5.4 PMI-Tabelle Karin Kress Kurzbeschreibung Die Abkürzung PMI steht für: „Plus“, „Minus“ und „Information“. Es handelt sich um eine Visualisierungsvariante in Tabellenform zur Entscheidungsvor-\nbereitung. Die Tabelle besteht aus drei großen Feldern. Die Gegenüberstel-\nlung von Vorteilen (Plus) und Nachteilen (Minus) wird ergänzt um ein drittes Feld, in das der oder die Ratsuchende offene Fragen eintragen kann. Gearbei-\ntet wird mit mehreren Tabellen. Für jede Handlungsoption wird eine eigene Tabelle angelegt. Diese Visualisierungsvariante kann besonders helfen, wenn der oder die Ratsuchende im Beratungsgespräch zwischen mehreren Optio-\nnen schwankt. Vor allem, wenn der oder die Ratsuchende viel über die jewei-\nligen Nachteile der Entscheidungsoptionen spricht, kann die Methode helfen, über die Informationsfragen zu konkreten Handlungsschritten zu kommen. Phase/Funktion: Anliegen: Material: Zeit: • Ausdruck\n• Stifte Sortieren verschiedener Handlungsoptionen Entscheidungsfindung ab 15"
      },
      {
        "rank": 2,
        "id": "8a13870c1e138251f72d2031f0a81d979276472cb1de16160c4456786e65275a",
        "score": 0.9893726706504822,
        "meta": {
          "file_path": "1001586-136-139.txt",
          "source_id": "971ef64c87ce6eeeeb6a4c0a76df2de0eeb3b6a5e1f7d2045594b018d8f00c67",
          "page_number": 3,
          "split_id": 4,
          "split_idx_start": 4428,
          "_split_overlap": [
            {
              "doc_id": "8442627039a0208851a6c3ad9c5c6aced010eea0cdb736bcb471b17733c0e4b1",
              "range": [
                1076,
                1466
              ]
            },
            {
              "doc_id": "eb6f9afa2afb4615e0d3af63e14efca3bd6beb5ab8965d6c9fd6875d659b402d",
              "range": [
                0,
                368
              ]
            }
          ]
        },
        "content": "Tabelle dem oder der Ratsuchenden auch unausge-\nfüllt als Anregung für eigene weitere Überlegungen mitgeben. Bei mehreren Beratungssitzungen kann das Anlegen der Tabelle zur Vorbereitung auf ein nächstes Gespräch dienen.\nKommentar zum Einsatz\nZielgruppe: Die Methode lässt sich, wenn Sie die Tabelle für die ratsuchende Person ausfüllen, auf viele Personenkreise anwenden. Für Ratsuchende, die selbst schon sehr strukturiert vorgehen, reicht es mitunter, das Modell zur Anliegen: Eigenbearbeitung vorzustellen. Entscheidungsvorbereitung zu verschiedenen Weiterbildungen, zwischen Weiterbildung oder beruflicher Umorientierung, zwischen privaten und beruflichen Prioritäten, zwischen zeitlich unterschiedlich umfangreichen Phase im Beratungsgespräch:\nOptionen. Das Beratungsgespräch sollte schon so weit fortgeschritten sein, dass sich auch verschiedene Entscheidungsvarianten abzeichnen. Die Methode ist daher eher am Ende der Mittelphase anzusie-\ndeln. Ergeben sich aus der Methode jedoch neue Frage"
      },
      {
        "rank": 3,
        "id": "73ddfffb5e1296b06702f140805a42d5d60954264c228c403bbafffe3fbee212",
        "score": 0.9740760922431946,
        "meta": {
          "file_path": "1001586-136-139.txt",
          "source_id": "971ef64c87ce6eeeeb6a4c0a76df2de0eeb3b6a5e1f7d2045594b018d8f00c67",
          "page_number": 1,
          "split_id": 1,
          "split_idx_start": 1205,
          "_split_overlap": [
            {
              "doc_id": "e5100cdcad40359f9757ff1846bb1ad22c026b190a15cd6a3da5e071fbf566ae",
              "range": [
                1205,
                1609
              ]
            },
            {
              "doc_id": "a8e2b6a1ea7e7e0040ccb7036118e5b3d58307ec92e7b31d53f2409c3cfc84f5",
              "range": [
                0,
                360
              ]
            }
          ]
        },
        "content": "vor unattrak-\ntiven Tätigkeiten + Orientierung\nNeue Erfahrungen\nNützliches tun\nEngagement macht sich gut im Lebens-\nlauf i: Welche Studienangebote gibt es?\nWie hoch sind die Mieten in meinen Wunschstädten? i: Wie läuft das FSJ ab?\nGehalt/Arbeitszeiten? Abb. 16: PMI-Tabellen (eigene Darstellung) 136 5 Methoden und Techniken\fAblauf der Beratung\nVorbereitung: 1. Die PMI-Tabelle können Sie als Kopie oder Ausdruck bereit- Methode einleiten: legen, oder auf einem A3-Bogen vorzeichnen. 2. Oft ergibt sich innerhalb des Beratungsgesprächs schon eine Situation, in welcher der oder die Ratsuchende über Vor- und Nachteile seiner Handlungsoptionen spricht. In diesem Fall können Sie die Tabelle auch aus einem leeren Blatt heraus entwickeln, indem Sie die ge-\nnannten Stichworte in den drei Abteilungen sortieren. Wenn Sie mit einem Vordruck arbeiten wollen, ist es hilfreich darauf hinzuweisen, dass der oder die Ratsuchende ja bereits einige Vor- und Nachteile genannt hat und die PMI-Tabelle eine Hilfe"
      },
      {
        "rank": 4,
        "id": "f6ff6d6d1768e6816dd01a918a4f154b2dd0f2c9b7c30681e36aa901d5f672bd",
        "score": 0.9599952101707458,
        "meta": {
          "file_path": "1001586-103-122.txt",
          "source_id": "703de242bbca21fb44a372f294b8d15e12e6513559c5c63aeb11c6ab02234406",
          "page_number": 13,
          "split_id": 30,
          "split_idx_start": 32796,
          "_split_overlap": [
            {
              "doc_id": "221bcb7f3389c88ac71f34a75dbcfb9625aa86e09d50651caf03dd1a94b7996f",
              "range": [
                1040,
                1342
              ]
            },
            {
              "doc_id": "c36aa2aea9eab41e184cb38bf4e81ba7efbb1c8f276b2f4946c9b8dd92c4d9b8",
              "range": [
                0,
                352
              ]
            }
          ]
        },
        "content": "etwas und Spiegeln kann ich über den Widerstand der Methode gegenüber ergrün-\nAnderes zu machen. Was genau ist es, was Sie daran stört?“; „Wann haben Sie den, was die ratsuchende Person stört. das erste Mal gemerkt, dass wir falsch abgebogen sind?“; „Ah, es hat Sie schon ir-\nritiert, als ich vorhin … und nicht … Was hätte Ihnen an dieser Stelle eher gehol-\nfen?“. Diese Fragen bereiten nicht zuletzt den Übergang zu einer Veränderung der Arbeitsweise vor. Es ist ein Zeichen von Vertrauen, wenn Ratsuchende offenlegen, wie es ihnen im Prozess ergeht. Die Ratsuchenden erwarten aus ihrer Alltagserfahrung, dass sich der Berater bzw. die Beraterin durch die Kri-\ntik vielleicht auch persönlich in Frage gestellt sieht. Es ist daher wichtig, sich beim Ratsuchenden für die Offenheit zu bedanken und deutlich zu machen, dass dies dazu beiträgt, stimmigere Vorgehensweisen zu entwickeln. Dies setzt voraus, dass ich als Beraterin oder Berater die Souveränität entwickle, Aussagen über die Methode nicht "
      },
      {
        "rank": 5,
        "id": "c8ba32f9e4ce38310a0e1d3d4f50d4b52c5dc551605c8687020fb1fecfb64960",
        "score": 0.9079358577728271,
        "meta": {
          "file_path": "1001586-191-206.txt",
          "source_id": "5996317b3d6fb495232e6fedeb0c860a654108106958d08f3a09b9eb5dd0c419",
          "page_number": 11,
          "split_id": 26,
          "split_idx_start": 28831,
          "_split_overlap": [
            {
              "doc_id": "926041ca9983a8cc3466d3a6f4ec220ba7a50b90fea4f03b4230fb564865679a",
              "range": [
                1100,
                1457
              ]
            },
            {
              "doc_id": "671305b8bfe84d811c9b86c0d980ae74c17c82244e33607f1b96696d1a0617a9",
              "range": [
                0,
                363
              ]
            }
          ]
        },
        "content": "in Richtung Therapien ist also wenig hilfreich und wird zudem von Ratsuchenden vermutlich eher als grenzüberschreitend oder sogar als Angriff erlebt. Es ist daher zunächst einmal wichtig, selbst die Grenzen des eigenen Be-\nratungsangebotes zu bemerken und auch akzeptieren zu können. Gerade bei sehr schwierigen Lebenslagen der Ratsuchenden ist es wichtig, die Situation nicht durch vorschnelle Lösungsvorschläge oder halbherzige Aufmunterun-\ngen zu verharmlosen. Die Ratsuchenden empfinden es in der Regel als wohl-\ntuend, wenn sie auf Personen treffen, die mit ihnen die Situation zunächst einfach aushalten. Ich kann als Beraterin oder Berater Empathie zeigen, bleibe aber im Rahmen meines Beratungssettings und meiner Rolle. Meiner Informationsaufgabe kann ich gerecht werden, indem ich z.B. auf psychosoziale Beratungsangebote in der Nähe verweise. Die Mitarbeiterin-\nnen und Mitarbeiter in diesen Einrichtungen können die Situation der Rat-\nsuchenden in der Regel besser einschätzen, selbst hel"
      }
    ]
  }
]